srv_hijacker/__init__.py
srv_hijacker/srv_hijacker.py
srv_hijacker_aws_service_discovery-0.1.0b3.dist-info/WHEEL
srv_hijacker_aws_service_discovery-0.1.0b3.dist-info/METADATA
srv_hijacker_aws_service_discovery-0.1.0b3.dist-info/RECORD
